devstack/__init__.py
devstack/main.py
devstack-0.1.3.dist-info/LICENSE
devstack-0.1.3.dist-info/METADATA
devstack-0.1.3.dist-info/WHEEL
devstack-0.1.3.dist-info/entry_points.txt
devstack-0.1.3.dist-info/RECORD
