Metadata-Version: 2.1
Name: devstack
Version: 0.1.3
Summary: A tool for managing docker swarm stacks
Home-page: https://pypi.org/project/devstack/
License: MIT
Keywords: docker,swarm,stack,dev
Author: Thomas Silvestre
Author-email: t.silvestre@gravitysoftware.be
Requires-Python: >=3.10,<4.0
Classifier: License :: OSI Approved :: MIT License
Classifier: Programming Language :: Python :: 3
Classifier: Programming Language :: Python :: 3.10
Classifier: Programming Language :: Python :: 3.11
Classifier: Programming Language :: Python :: 3.12
Requires-Dist: pyyaml (>=6.0.2,<7.0.0)
Requires-Dist: typer (>=0.12.5,<0.13.0)
Project-URL: Repository, https://gitlab.com/gravitysoftware/devstack
